MANIFEST.in
README.rst
requirements.txt
setup.py
graphite_aws_cleaner/__init__.py
graphite_aws_cleaner/cleaner.py
graphite_aws_cleaner/cli.py
graphite_aws_cleaner.egg-info/PKG-INFO
graphite_aws_cleaner.egg-info/SOURCES.txt
graphite_aws_cleaner.egg-info/dependency_links.txt
graphite_aws_cleaner.egg-info/entry_points.txt
graphite_aws_cleaner.egg-info/not-zip-safe
graphite_aws_cleaner.egg-info/requires.txt
graphite_aws_cleaner.egg-info/top_level.txt