Metadata-Version: 1.1
Name: graphite-aws-cleaner
Version: 0.0.3
Summary: Delete old graphite data based on instance name patternand current running AWS instances.
Home-page: https://github.com/Yipit/graphite_aws_cleaner
Author: Yipit Coders
Author-email: coders@yipit.com
License: UNKNOWN
Platform: UNKNOWN
Classifier: Programming Language :: Python
